{
  "QuantumChipArch": {
    "QubitCount": 72,
    "CLOPS" : 370,
    "HighFrequencyQubit": [
      0,
      9,
      11,
      16,
      12,
      19,
      14,
      18,
      24,
      2,
      7,
      25,
      26,
      28,
      31,
      33,
      35,
      36,
      38,
      40,
      4,
      45,
      47,
      48,
      50,
      52,
      60,
      57,
      62,
      67,
      71
    ],
    "CompensateAngle": {
      "CZ(0,1)": {
        "0": 3.62,
        "1": 3.56
      },
      "CZ(0,6)": {
        "0": 3.435,
        "6": 5.99
      },
      "CZ(9,15)": {
        "9": 1.71,
        "15": 1.71
      },
      "CZ(10,11)": {
        "10": 4.5,
        "11": 5.73
      },
      "CZ(10,16)": {
        "10": 1.6402397751975857,
        "16": 1.839591521847356
      },
      "CZ(11,17)": {
        "11": 0.0,
        "17": 5.45
      },
      "CZ(12,13)": {
        "12": 4.276462783611285,
        "13": 3.074845352759239
      },
      "CZ(12,18)": {
        "12": 3.4,
        "18": 2.21
      },
      "CZ(13,19)": {
        "13": 3.962625890823809,
        "19": 5.140403210312815
      },
      "CZ(14,15)": {
        "14": 1.2622553802583204,
        "15": 3.583989349270316
      },
      "CZ(14,20)": {
        "14": 4.94,
        "20": 0.14
      },
      "CZ(15,16)": {
        "15": 0.13,
        "16": 4.51
      },
      "CZ(16,17)": {
        "16": 2.4,
        "17": 4.45
      },
      "CZ(16,22)": {
        "16": 0.86,
        "22": 2.07
      },
      "CZ(18,19)": {
        "18": 0.153125,
        "19": 4.3125
      },
      "CZ(18,24)": {
        "18": 5.7,
        "24": 0.98
      },
      "CZ(1,2)": {
        "1": 2.92,
        "2": 4.89
      },
      "CZ(1,7)": {
        "1": 3.1459317223289129,
        "7": 4.606753326559266
      },
      "CZ(19,20)": {
        "19": 0.26,
        "20": 5.1
      },
      "CZ(19,25)": {
        "19": 2.54,
        "25": 0.7
      },
      "CZ(20,26)": {
        "20": 2.82,
        "26": 6.13
      },
      "CZ(22,28)": {
        "22": 1.383267700849661,
        "28": 6.008424431898595
      },
      "CZ(24,25)": {
        "24": 3.0825627681084848,
        "25": 0.4701148565431379
      },
      "CZ(24,30)": {
        "24": 4.029999999999999,
        "30": 5.665
      },
      "CZ(25,26)": {
        "25": 5.4,
        "26": 4.39
      },
      "CZ(25,31)": {
        "25": 0.8718234436017932,
        "31": 0.4738468322546484
      },
      "CZ(26,27)": {
        "26": 0.0,
        "27": 5.32
      },
      "CZ(26,32)": {
        "26": 2.62,
        "32": 4.7
      },
      "CZ(27,28)": {
        "27": 2.75,
        "28": 5.49
      },
      "CZ(27,33)": {
        "27": 4.080625,
        "33": 1.48375
      },
      "CZ(28,29)": {
        "28": 0.4017688950469376,
        "29": 3.9090107772889746
      },
      "CZ(28,34)": {
        "28": 3.34,
        "34": 3.24
      },
      "CZ(2,3)": {
        "2": 2.57,
        "3": 6.04
      },
      "CZ(2,8)": {
        "2": 0.86,
        "8": 3.91
      },
      "CZ(29,35)": {
        "29": 5.9975000000000009,
        "35": 3.1825
      },
      "CZ(30,31)": {
        "30": 2.8436113103711637,
        "31": 2.760242005602442
      },
      "CZ(30,36)": {
        "30": 5.306875,
        "36": 5.2125
      },
      "CZ(31,32)": {
        "31": 0.2253949456272748,
        "32": 3.1627464024154849
      },
      "CZ(31,37)": {
        "31": 4.03937618587679,
        "37": 1.1093064620280453
      },
      "CZ(32,33)": {
        "32": 5.93,
        "33": 0.13
      },
      "CZ(32,38)": {
        "32": 5.54,
        "38": 3.73
      },
      "CZ(33,34)": {
        "33": 0.9144143935295022,
        "34": 5.099997382738643
      },
      "CZ(33,39)": {
        "33": 6.4375,
        "39": 1.6275
      },
      "CZ(34,35)": {
        "34": 4.415,
        "35": 4.825
      },
      "CZ(34,40)": {
        "34": 3.9775,
        "40": 3.0
      },
      "CZ(35,41)": {
        "35": 2.526906564231661,
        "41": 3.760492565722405
      },
      "CZ(36,37)": {
        "36": 5.785,
        "37": 1.545
      },
      "CZ(36,42)": {
        "36": 1.0961048636600069,
        "42": 5.810172912830167
      },
      "CZ(37,38)": {
        "37": 5.15,
        "38": 4.4
      },
      "CZ(38,39)": {
        "38": 0.22,
        "39": 2.595
      },
      "CZ(38,44)": {
        "38": 0.33,
        "44": 3.07
      },
      "CZ(3,9)": {
        "3": 0.0,
        "9": 0.54
      },
      "CZ(3,4)": {
        "3": 5.65,
        "4": 2.1
      },
      "CZ(39,40)": {
        "39": 4.31,
        "40": 2.8
      },
      "CZ(39,45)": {
        "39": 6.073110260793558,
        "45": 2.39795490272003
      },
      "CZ(40,41)": {
        "40": 2.6307262285864088,
        "41": -0.9003266371751593
      },
      "CZ(40,46)": {
        "40": 4.37725549830503,
        "46": -0.2354836393216268
      },
      "CZ(41,47)": {
        "41": 5.645,
        "47": 0.0
      },
      "CZ(42,48)": {
        "42": 4.521471995961905,
        "48": 4.380175924836751
      },
      "CZ(44,45)": {
        "44": 5.39,
        "45": 5.82
      },
      "CZ(44,50)": {
        "44": 4.09746026605101,
        "50": 3.032578603248493
      },
      "CZ(46,47)": {
        "46": 3.95,
        "47": 5.93
      },
      "CZ(46,52)": {
        "46": 5.8,
        "52": 0.2
      },
      "CZ(48,49)": {
        "48": 2.42,
        "49": 0.13
      },
      "CZ(48,54)": {
        "48": 2.6255084326532769,
        "54": 2.610066863938227
      },
      "CZ(4,10)": {
        "4": 4.984349535961469,
        "10": 5.219845056878602
      },
      "CZ(49,50)": {
        "49": 0.4894475414187035,
        "50": 1.116949772139525
      },
      "CZ(50,56)": {
        "50": 4.814054358357943,
        "56": 1.097753028026428
      },
      "CZ(54,60)": {
        "54": 3.893317390474551,
        "60": 2.735235468839408
      },
      "CZ(56,57)": {
        "56": 5.948964356290856,
        "57": 1.426240373924968
      },
      "CZ(56,62)": {
        "56": 3.98,
        "62": 1.42
      },
      "CZ(60,61)": {
        "60": 1.1606288243319325,
        "61": 2.8242996240931874
      },
      "CZ(60,66)": {
        "60": 5.392141323961576,
        "66": 0.1266320475765914
      },
      "CZ(61,62)": {
        "61": 1.68,
        "62": 4.047499999999999
      },
      "CZ(61,67)": {
        "61": 5.52755511326126,
        "67": 5.938781641911454
      },
      "CZ(62,68)": {
        "62": 1.9050791680731865,
        "68": 3.488126504750189
      },
      "CZ(65,71)": {
        "65": 2.772963892447944,
        "71": 2.872810774241835
      },
      "CZ(67,68)": {
        "67": 5.71005291673348,
        "68": 0.08043070985953929
      },
      "CZ(6,12)": {
        "6": 5.320145776889303,
        "12": 4.277112094332661
      },
      "CZ(6,7)": {
        "6": 2.66,
        "7": 2.61
      },
      "CZ(70,71)": {
        "70": 0.56,
        "71": 5.88
      },
      "CZ(7,13)": {
        "7": 0.15,
        "13": 5.88
      },
      "CZ(7,8)": {
        "7": 5.06,
        "8": 1.23
      },
      "CZ(8,14)": {
        "8": 0.85,
        "14": 3.25
      }
    },
    "AdjMatrix": {
      "0": [
        {
          "v": 1,
          "w": 0.9812
        },
        {
          "v": 6,
          "w": 0.9825
        }
      ],
      "1": [
        {
          "v": 0,
          "w": 0.9812
        },
        {
          "v": 2,
          "w": 0.9686
        },
        {
          "v": 7,
          "w": 0.9727
        }
      ],
      "2": [
        {
          "v": 1,
          "w": 0.9686
        },
        {
          "v": 3,
          "w": 0.9825
        },
        {
          "v": 8,
          "w": 0.9674
        }
      ],
      "3": [
        {
          "v": 2,
          "w": 0.9825
        },
        {
          "v": 4,
          "w": 0.9867
        },
        {
          "v": 9,
          "w": 0.9679
        }
      ],
      "4": [
        {
          "v": 3,
          "w": 0.9867
        },
        {
          "v": 10,
          "w": 0.9676
        }
      ],
      "6": [
        {
          "v": 0,
          "w": 0.9825
        },
        {
          "v": 7,
          "w": 0.9641
        },
        {
          "v": 12,
          "w": 0.9794
        }
      ],
      "7": [
        {
          "v": 1,
          "w": 0.9727
        },
        {
          "v": 6,
          "w": 0.9641
        },
        {
          "v": 8,
          "w": 0.9642
        },
        {
          "v": 13,
          "w": 0.9691
        }
      ],
      "8": [
        {
          "v": 2,
          "w": 0.9674
        },
        {
          "v": 7,
          "w": 0.9642
        },
        {
          "v": 14,
          "w": 0.9595
        }
      ],
      "9": [
        {
          "v": 3,
          "w": 0.9679
        },
        {
          "v": 15,
          "w": 0.9501
        }
      ],
      "10": [
        {
          "v": 4,
          "w": 0.9676
        },
        {
          "v": 11,
          "w": 0.9683
        },
        {
          "v": 16,
          "w": 0.958
        }
      ],
      "11": [
        {
          "v": 10,
          "w": 0.9683
        },
        {
          "v": 17,
          "w": 0.9732
        }
      ],
      "12": [
        {
          "v": 6,
          "w": 0.9794
        },
        {
          "v": 13,
          "w": 0.9823
        },
        {
          "v": 18,
          "w": 0.9405
        }
      ],
      "13": [
        {
          "v": 7,
          "w": 0.9691
        },
        {
          "v": 12,
          "w": 0.9823
        },
        {
          "v": 19,
          "w": 0.9155
        }
      ],
      "14": [
        {
          "v": 8,
          "w": 0.9595
        },
        {
          "v": 15,
          "w": 0.9609
        },
        {
          "v": 20,
          "w": 0.9641
        }
      ],
      "15": [
        {
          "v": 9,
          "w": 0.9501
        },
        {
          "v": 14,
          "w": 0.9609
        },
        {
          "v": 16,
          "w": 0.9689
        }
      ],
      "16": [
        {
          "v": 10,
          "w": 0.958
        },
        {
          "v": 15,
          "w": 0.9689
        },
        {
          "v": 17,
          "w": 0.9843
        },
        {
          "v": 22,
          "w": 0.9817
        }
      ],
      "17": [
        {
          "v": 11,
          "w": 0.9732
        },
        {
          "v": 16,
          "w": 0.9843
        }
      ],
      "18": [
        {
          "v": 12,
          "w": 0.9405
        },
        {
          "v": 19,
          "w": 0.9616
        },
        {
          "v": 24,
          "w": 0.9744
        }
      ],
      "19": [
        {
          "v": 13,
          "w": 0.9155
        },
        {
          "v": 18,
          "w": 0.9616
        },
        {
          "v": 20,
          "w": 0.9125
        },
        {
          "v": 25,
          "w": 0.9796
        }
      ],
      "20": [
        {
          "v": 14,
          "w": 0.9641
        },
        {
          "v": 19,
          "w": 0.9125
        },
        {
          "v": 26,
          "w": 0.9623
        }
      ],
      "22": [
        {
          "v": 16,
          "w": 0.9817
        },
        {
          "v": 28,
          "w": 0.9247
        }
      ],
      "24": [
        {
          "v": 18,
          "w": 0.9744
        },
        {
          "v": 25,
          "w": 0.9611
        },
        {
          "v": 30,
          "w": 0.985
        }
      ],
      "25": [
        {
          "v": 19,
          "w": 0.9796
        },
        {
          "v": 24,
          "w": 0.9611
        },
        {
          "v": 26,
          "w": 0.9769
        },
        {
          "v": 31,
          "w": 0.9614
        }
      ],
      "26": [
        {
          "v": 20,
          "w": 0.9623
        },
        {
          "v": 25,
          "w": 0.9769
        },
        {
          "v": 27,
          "w": 0.9659
        },
        {
          "v": 32,
          "w": 0.976
        }
      ],
      "27": [
        {
          "v": 26,
          "w": 0.9659
        },
        {
          "v": 28,
          "w": 0.9736
        },
        {
          "v": 33,
          "w": 0.9857
        }
      ],
      "28": [
        {
          "v": 22,
          "w": 0.9247
        },
        {
          "v": 27,
          "w": 0.9736
        },
        {
          "v": 29,
          "w": 0.9805
        },
        {
          "v": 34,
          "w": 0.9762
        }
      ],
      "29": [
        {
          "v": 28,
          "w": 0.9805
        },
        {
          "v": 35,
          "w": 0.9527
        }
      ],
      "30": [
        {
          "v": 24,
          "w": 0.985
        },
        {
          "v": 31,
          "w": 0.9565
        },
        {
          "v": 36,
          "w": 0.956
        }
      ],
      "31": [
        {
          "v": 25,
          "w": 0.9614
        },
        {
          "v": 30,
          "w": 0.9565
        },
        {
          "v": 32,
          "w": 0.9752
        },
        {
          "v": 37,
          "w": 0.9244
        }
      ],
      "32": [
        {
          "v": 26,
          "w": 0.976
        },
        {
          "v": 31,
          "w": 0.9752
        },
        {
          "v": 33,
          "w": 0.9588
        },
        {
          "v": 38,
          "w": 0.9848
        }
      ],
      "33": [
        {
          "v": 27,
          "w": 0.9857
        },
        {
          "v": 32,
          "w": 0.9588
        },
        {
          "v": 34,
          "w": 0.9507
        },
        {
          "v": 39,
          "w": 0.961
        }
      ],
      "34": [
        {
          "v": 28,
          "w": 0.9762
        },
        {
          "v": 33,
          "w": 0.9507
        },
        {
          "v": 35,
          "w": 0.9852
        },
        {
          "v": 40,
          "w": 0.9806
        }
      ],
      "35": [
        {
          "v": 29,
          "w": 0.9527
        },
        {
          "v": 34,
          "w": 0.9852
        },
        {
          "v": 41,
          "w": 0.971
        }
      ],
      "36": [
        {
          "v": 30,
          "w": 0.956
        },
        {
          "v": 37,
          "w": 0.9745
        },
        {
          "v": 42,
          "w": 0.9143
        }
      ],
      "37": [
        {
          "v": 31,
          "w": 0.9244
        },
        {
          "v": 36,
          "w": 0.9745
        },
        {
          "v": 38,
          "w": 0.9565
        }
      ],
      "38": [
        {
          "v": 32,
          "w": 0.9848
        },
        {
          "v": 37,
          "w": 0.9565
        },
        {
          "v": 39,
          "w": 0.9758
        },
        {
          "v": 44,
          "w": 0.9585
        }
      ],
      "39": [
        {
          "v": 33,
          "w": 0.961
        },
        {
          "v": 38,
          "w": 0.9758
        },
        {
          "v": 40,
          "w": 0.9778
        },
        {
          "v": 45,
          "w": 0.8887
        }
      ],
      "40": [
        {
          "v": 34,
          "w": 0.9806
        },
        {
          "v": 39,
          "w": 0.9778
        },
        {
          "v": 41,
          "w": 0.9605
        },
        {
          "v": 46,
          "w": 0.9243
        }
      ],
      "41": [
        {
          "v": 35,
          "w": 0.971
        },
        {
          "v": 40,
          "w": 0.9605
        },
        {
          "v": 47,
          "w": 0.9528
        }
      ],
      "42": [
        {
          "v": 36,
          "w": 0.9143
        },
        {
          "v": 48,
          "w": 0.9944
        }
      ],
      "44": [
        {
          "v": 38,
          "w": 0.9585
        },
        {
          "v": 45,
          "w": 0.9748
        },
        {
          "v": 50,
          "w": 0.9163
        }
      ],
      "45": [
        {
          "v": 39,
          "w": 0.8887
        },
        {
          "v": 44,
          "w": 0.9748
        }
      ],
      "46": [
        {
          "v": 40,
          "w": 0.9243
        },
        {
          "v": 47,
          "w": 0.9806
        },
        {
          "v": 52,
          "w": 0.9838
        }
      ],
      "47": [
        {
          "v": 41,
          "w": 0.9528
        },
        {
          "v": 46,
          "w": 0.9806
        }
      ],
      "48": [
        {
          "v": 42,
          "w": 0.9944
        },
        {
          "v": 49,
          "w": 0.986
        },
        {
          "v": 54,
          "w": 0.9216
        }
      ],
      "49": [
        {
          "v": 48,
          "w": 0.986
        },
        {
          "v": 50,
          "w": 0.9749
        }
      ],
      "50": [
        {
          "v": 44,
          "w": 0.9163
        },
        {
          "v": 49,
          "w": 0.9749
        },
        {
          "v": 56,
          "w": 0.9731
        }
      ],
      "52": [
        {
          "v": 46,
          "w": 0.9838
        }
      ],
      "54": [
        {
          "v": 48,
          "w": 0.9216
        },
        {
          "v": 60,
          "w": 0.9418
        }
      ],
      "56": [
        {
          "v": 50,
          "w": 0.9731
        },
        {
          "v": 57,
          "w": 0.9381
        },
        {
          "v": 62,
          "w": 0.9675
        }
      ],
      "57": [
        {
          "v": 56,
          "w": 0.9381
        }
      ],
      "60": [
        {
          "v": 54,
          "w": 0.9418
        },
        {
          "v": 61,
          "w": 0.9728
        },
        {
          "v": 66,
          "w": 0.9817
        }
      ],
      "61": [
        {
          "v": 60,
          "w": 0.9728
        },
        {
          "v": 62,
          "w": 0.9527
        },
        {
          "v": 67,
          "w": 0.9602
        }
      ],
      "62": [
        {
          "v": 56,
          "w": 0.9675
        },
        {
          "v": 61,
          "w": 0.9527
        },
        {
          "v": 68,
          "w": 0.9612
        }
      ],
      "65": [
        {
          "v": 71,
          "w": 0.9816
        }
      ],
      "66": [
        {
          "v": 60,
          "w": 0.9817
        }
      ],
      "67": [
        {
          "v": 61,
          "w": 0.9602
        },
        {
          "v": 68,
          "w": 0.9288
        }
      ],
      "68": [
        {
          "v": 62,
          "w": 0.9612
        },
        {
          "v": 67,
          "w": 0.9288
        }
      ],
      "70": [
        {
          "v": 71,
          "w": 0.9865
        }
      ],
      "71": [
        {
          "v": 65,
          "w": 0.9816
        },
        {
          "v": 70,
          "w": 0.9865
        }
      ]
    },
    "QubitParams": {
      "0": {
        "Frequency": 4175,
        "T1": 11.374,
        "T2": 2.841,
        "ReadoutFidelity": 0.8635,
        "SingleGateFidelity": 0.9979,
        "FidelityMat": [
          [
            0.91,
            0.183
          ],
          [
            0.09,
            0.817
          ]
        ]
      },
      "1": {
        "Frequency": 4313,
        "T1": 18.639,
        "T2": 2.095,
        "ReadoutFidelity": 0.8802,
        "SingleGateFidelity": 0.9981,
        "FidelityMat": [
          [
            0.9048,
            0.1444
          ],
          [
            0.0952,
            0.8556
          ]
        ]
      },
      "2": {
        "Frequency": 4660,
        "T1": 10.491,
        "T2": 1.302,
        "ReadoutFidelity": 0.8803,
        "SingleGateFidelity": 0.9974,
        "FidelityMat": [
          [
            0.9204,
            0.1598
          ],
          [
            0.0796,
            0.8402
          ]
        ]
      },
      "3": {
        "Frequency": 4107,
        "T1": 20.679,
        "T2": 0.937,
        "ReadoutFidelity": 0.9098,
        "SingleGateFidelity": 0.9958,
        "FidelityMat": [
          [
            0.939,
            0.1194
          ],
          [
            0.061,
            0.8806
          ]
        ]
      },
      "4": {
        "Frequency": 4180.919,
        "T1": 10.811,
        "T2": 3.087,
        "ReadoutFidelity": 0.8831,
        "SingleGateFidelity": 0.9987,
        "FidelityMat": [
          [
            0.9234,
            0.1572
          ],
          [
            0.0766,
            0.8428
          ]
        ]
      },
      "6": {
        "Frequency": 4094,
        "T1": 7.181,
        "T2": 1.206,
        "ReadoutFidelity": 0.9214,
        "SingleGateFidelity": 0.998,
        "FidelityMat": [
          [
            0.9326,
            0.0898
          ],
          [
            0.0674,
            0.9102
          ]
        ]
      },
      "7": {
        "Frequency": 4618,
        "T1": 8.027,
        "T2": 1.451,
        "ReadoutFidelity": 0.8952,
        "SingleGateFidelity": 0.9952,
        "FidelityMat": [
          [
            0.9388,
            0.1484
          ],
          [
            0.0612,
            0.8516
          ]
        ]
      },
      "8": {
        "Frequency": 4146,
        "T1": 11.068,
        "T2": 1.214,
        "ReadoutFidelity": 0.8381,
        "SingleGateFidelity": 0.9974,
        "FidelityMat": [
          [
            0.9346,
            0.2584
          ],
          [
            0.0654,
            0.7416
          ]
        ]
      },
      "9": {
        "Frequency": 4978,
        "T1": 6.207,
        "T2": 1.817,
        "ReadoutFidelity": 0.8939,
        "SingleGateFidelity": 0.996,
        "FidelityMat": [
          [
            0.9166,
            0.1288
          ],
          [
            0.0834,
            0.8712
          ]
        ]
      },
      "10": {
        "Frequency": 4260,
        "T1": 35.472,
        "T2": 1.21,
        "ReadoutFidelity": 0.8853,
        "SingleGateFidelity": 0.9979,
        "FidelityMat": [
          [
            0.9242,
            0.1536
          ],
          [
            0.0758,
            0.8464
          ]
        ]
      },
      "11": {
        "Frequency": 4799,
        "T1": 17.27,
        "T2": 1.466,
        "ReadoutFidelity": 0.9263,
        "SingleGateFidelity": 0.9972,
        "FidelityMat": [
          [
            0.9414,
            0.0888
          ],
          [
            0.0586,
            0.9112
          ]
        ]
      },
      "12": {
        "Frequency": 4658,
        "T1": 13.374,
        "T2": 4.054,
        "ReadoutFidelity": 0.9191,
        "SingleGateFidelity": 0.9978,
        "FidelityMat": [
          [
            0.959,
            0.1208
          ],
          [
            0.041,
            0.8792
          ]
        ]
      },
      "13": {
        "Frequency": 4000,
        "T1": 13.945,
        "T2": 0.694,
        "ReadoutFidelity": 0.8964,
        "SingleGateFidelity": 0.9983,
        "FidelityMat": [
          [
            0.9402,
            0.1474
          ],
          [
            0.0598,
            0.8526
          ]
        ]
      },
      "14": {
        "Frequency": 4530.15,
        "T1": 10.432,
        "T2": 1.337,
        "ReadoutFidelity": 0.8926,
        "SingleGateFidelity": 0.998,
        "FidelityMat": [
          [
            0.9574,
            0.1722
          ],
          [
            0.0426,
            0.8278
          ]
        ]
      },
      "15": {
        "Frequency": 4075,
        "T1": 12.073,
        "T2": 1.139,
        "ReadoutFidelity": 0.8945,
        "SingleGateFidelity": 0.9962,
        "FidelityMat": [
          [
            0.919,
            0.13
          ],
          [
            0.081,
            0.87
          ]
        ]
      },
      "16": {
        "Frequency": 4624,
        "T1": 10.8,
        "T2": 1.033,
        "ReadoutFidelity": 0.874,
        "SingleGateFidelity": 0.9976,
        "FidelityMat": [
          [
            0.8992,
            0.1512
          ],
          [
            0.1008,
            0.8488
          ]
        ]
      },
      "17": {
        "Frequency": 4147,
        "T1": 11.083,
        "T2": 1.452,
        "ReadoutFidelity": 0.8786,
        "SingleGateFidelity": 0.9972,
        "FidelityMat": [
          [
            0.9224,
            0.1652
          ],
          [
            0.0776,
            0.8348
          ]
        ]
      },
      "18": {
        "Frequency": 4302,
        "T1": 18.171,
        "T2": 1.666,
        "ReadoutFidelity": 0.9078,
        "SingleGateFidelity": 0.9976,
        "FidelityMat": [
          [
            0.944,
            0.1284
          ],
          [
            0.056,
            0.8716
          ]
        ]
      },
      "19": {
        "Frequency": 4143.184,
        "T1": 16.625,
        "T2": 1.62,
        "ReadoutFidelity": 0.8793,
        "SingleGateFidelity": 0.9973,
        "FidelityMat": [
          [
            0.9132,
            0.1546
          ],
          [
            0.0868,
            0.8454
          ]
        ]
      },
      "20": {
        "Frequency": 4177.158,
        "T1": 15.382,
        "T2": 0.0,
        "ReadoutFidelity": 0.9099,
        "SingleGateFidelity": 0.9982,
        "FidelityMat": [
          [
            0.9576,
            0.1378
          ],
          [
            0.0424,
            0.8622
          ]
        ]
      },
      "22": {
        "Frequency": 4215,
        "T1": 7.63,
        "T2": 1.605,
        "ReadoutFidelity": 0.8905,
        "SingleGateFidelity": 0.9953,
        "FidelityMat": [
          [
            0.9434,
            0.1624
          ],
          [
            0.0566,
            0.8376
          ]
        ]
      },
      "24": {
        "Frequency": 4491,
        "T1": 17.231,
        "T2": 1.219,
        "ReadoutFidelity": 0.8896,
        "SingleGateFidelity": 0.998,
        "FidelityMat": [
          [
            0.8932,
            0.114
          ],
          [
            0.1068,
            0.886
          ]
        ]
      },
      "25": {
        "Frequency": 4122,
        "T1": 29.357,
        "T2": 1.031,
        "ReadoutFidelity": 0.8833,
        "SingleGateFidelity": 0.9964,
        "FidelityMat": [
          [
            0.9072,
            0.1406
          ],
          [
            0.0928,
            0.8594
          ]
        ]
      },
      "26": {
        "Frequency": 4653,
        "T1": 13.167,
        "T2": 1.34,
        "ReadoutFidelity": 0.7245,
        "SingleGateFidelity": 0.9983,
        "FidelityMat": [
          [
            0.9592,
            0.5102
          ],
          [
            0.0408,
            0.4898
          ]
        ]
      },
      "27": {
        "Frequency": 4106,
        "T1": 11.031,
        "T2": 1.564,
        "ReadoutFidelity": 0.8779,
        "SingleGateFidelity": 0.9975,
        "FidelityMat": [
          [
            0.8932,
            0.1374
          ],
          [
            0.1068,
            0.8626
          ]
        ]
      },
      "28": {
        "Frequency": 4568,
        "T1": 9.345,
        "T2": 1.337,
        "ReadoutFidelity": 0.9218,
        "SingleGateFidelity": 0.9976,
        "FidelityMat": [
          [
            0.939,
            0.0954
          ],
          [
            0.061,
            0.9046
          ]
        ]
      },
      "29": {
        "Frequency": 4036,
        "T1": 12.784,
        "T2": 2.971,
        "ReadoutFidelity": 0.8951,
        "SingleGateFidelity": 0.9968,
        "FidelityMat": [
          [
            0.937,
            0.1468
          ],
          [
            0.063,
            0.8532
          ]
        ]
      },
      "30": {
        "Frequency": 4159,
        "T1": 17.215,
        "T2": 1.95,
        "ReadoutFidelity": 0.9212,
        "SingleGateFidelity": 0.9983,
        "FidelityMat": [
          [
            0.9506,
            0.1082
          ],
          [
            0.0494,
            0.8918
          ]
        ]
      },
      "31": {
        "Frequency": 4570,
        "T1": 15.441,
        "T2": 1.997,
        "ReadoutFidelity": 0.8167,
        "SingleGateFidelity": 0.9952,
        "FidelityMat": [
          [
            0.872,
            0.2386
          ],
          [
            0.128,
            0.7614
          ]
        ]
      },
      "32": {
        "Frequency": 4007,
        "T1": 14.759,
        "T2": 2.487,
        "ReadoutFidelity": 0.8826,
        "SingleGateFidelity": 0.9977,
        "FidelityMat": [
          [
            0.918,
            0.1528
          ],
          [
            0.082,
            0.8472
          ]
        ]
      },
      "33": {
        "Frequency": 4620,
        "T1": 11.445,
        "T2": 1.982,
        "ReadoutFidelity": 0.8976,
        "SingleGateFidelity": 0.998,
        "FidelityMat": [
          [
            0.9638,
            0.1686
          ],
          [
            0.0362,
            0.8314
          ]
        ]
      },
      "34": {
        "Frequency": 4072,
        "T1": 0.0,
        "T2": 1.69,
        "ReadoutFidelity": 0.8755,
        "SingleGateFidelity": 0.9976,
        "FidelityMat": [
          [
            0.9092,
            0.1582
          ],
          [
            0.0908,
            0.8418
          ]
        ]
      },
      "35": {
        "Frequency": 4454,
        "T1": 28.937,
        "T2": 1.792,
        "ReadoutFidelity": 0.9269,
        "SingleGateFidelity": 0.9951,
        "FidelityMat": [
          [
            0.953,
            0.0992
          ],
          [
            0.047,
            0.9008
          ]
        ]
      },
      "36": {
        "Frequency": 4622,
        "T1": 13.622,
        "T2": 2.196,
        "ReadoutFidelity": 0.8812,
        "SingleGateFidelity": 0.9978,
        "FidelityMat": [
          [
            0.9168,
            0.1544
          ],
          [
            0.0832,
            0.8456
          ]
        ]
      },
      "37": {
        "Frequency": 4045,
        "T1": 9.856,
        "T2": 1.618,
        "ReadoutFidelity": 0.8514,
        "SingleGateFidelity": 0.9976,
        "FidelityMat": [
          [
            0.9042,
            0.2014
          ],
          [
            0.0958,
            0.7986
          ]
        ]
      },
      "38": {
        "Frequency": 4498,
        "T1": 18.869,
        "T2": 1.277,
        "ReadoutFidelity": 0.9019,
        "SingleGateFidelity": 0.997,
        "FidelityMat": [
          [
            0.9306,
            0.1268
          ],
          [
            0.0694,
            0.8732
          ]
        ]
      },
      "39": {
        "Frequency": 4178,
        "T1": 10.05,
        "T2": 1.27,
        "ReadoutFidelity": 0.9284,
        "SingleGateFidelity": 0.9969,
        "FidelityMat": [
          [
            0.9512,
            0.0944
          ],
          [
            0.0488,
            0.9056
          ]
        ]
      },
      "40": {
        "Frequency": 4283.349,
        "T1": 30.834,
        "T2": 1.21,
        "ReadoutFidelity": 0.8911,
        "SingleGateFidelity": 0.996,
        "FidelityMat": [
          [
            0.9592,
            0.177
          ],
          [
            0.0408,
            0.823
          ]
        ]
      },
      "41": {
        "Frequency": 4083,
        "T1": 26.763,
        "T2": 1.823,
        "ReadoutFidelity": 0.9068,
        "SingleGateFidelity": 0.9981,
        "FidelityMat": [
          [
            0.922,
            0.1084
          ],
          [
            0.078,
            0.8916
          ]
        ]
      },
      "42": {
        "Frequency": 4244,
        "T1": 13.037,
        "T2": 3.095,
        "ReadoutFidelity": 0.8856,
        "SingleGateFidelity": 0.9981,
        "FidelityMat": [
          [
            0.9312,
            0.16
          ],
          [
            0.0688,
            0.84
          ]
        ]
      },
      "44": {
        "Frequency": 4333,
        "T1": 8.796,
        "T2": 2.279,
        "ReadoutFidelity": 0.8265,
        "SingleGateFidelity": 0.9981,
        "FidelityMat": [
          [
            0.9686,
            0.3156
          ],
          [
            0.0314,
            0.6844
          ]
        ]
      },
      "45": {
        "Frequency": 4804,
        "T1": 11.261,
        "T2": 2.151,
        "ReadoutFidelity": 0.8871,
        "SingleGateFidelity": 0.9977,
        "FidelityMat": [
          [
            0.9206,
            0.1464
          ],
          [
            0.0794,
            0.8536
          ]
        ]
      },
      "46": {
        "Frequency": 4001.0,
        "T1": 27.095,
        "T2": 2.019,
        "ReadoutFidelity": 0.8383,
        "SingleGateFidelity": 0.9972,
        "FidelityMat": [
          [
            0.9066,
            0.23
          ],
          [
            0.0934,
            0.77
          ]
        ]
      },
      "47": {
        "Frequency": 4391,
        "T1": 20.758,
        "T2": 1.539,
        "ReadoutFidelity": 0.9045,
        "SingleGateFidelity": 0.9972,
        "FidelityMat": [
          [
            0.9268,
            0.1178
          ],
          [
            0.0732,
            0.8822
          ]
        ]
      },
      "48": {
        "Frequency": 4178,
        "T1": 14.515,
        "T2": 0.585,
        "ReadoutFidelity": 0.8645,
        "SingleGateFidelity": 0.9988,
        "FidelityMat": [
          [
            0.8968,
            0.1678
          ],
          [
            0.1032,
            0.8322
          ]
        ]
      },
      "49": {
        "Frequency": 4055,
        "T1": 14.771,
        "T2": 2.144,
        "ReadoutFidelity": 0.8992,
        "SingleGateFidelity": 0.9984,
        "FidelityMat": [
          [
            0.9474,
            0.149
          ],
          [
            0.0526,
            0.851
          ]
        ]
      },
      "50": {
        "Frequency": 4699,
        "T1": 12.16,
        "T2": 1.553,
        "ReadoutFidelity": 0.8676,
        "SingleGateFidelity": 0.9959,
        "FidelityMat": [
          [
            0.9254,
            0.1902
          ],
          [
            0.0746,
            0.8098
          ]
        ]
      },
      "52": {
        "Frequency": 4464,
        "T1": 14.56,
        "T2": 1.968,
        "ReadoutFidelity": 0.9252,
        "SingleGateFidelity": 0.9977,
        "FidelityMat": [
          [
            0.9458,
            0.0954
          ],
          [
            0.0542,
            0.9046
          ]
        ]
      },
      "54": {
        "Frequency": 4087,
        "T1": 0.0,
        "T2": 1.475,
        "ReadoutFidelity": 0.867,
        "SingleGateFidelity": 0.9979,
        "FidelityMat": [
          [
            0.8968,
            0.1628
          ],
          [
            0.1032,
            0.8372
          ]
        ]
      },
      "56": {
        "Frequency": 4419,
        "T1": 8.377,
        "T2": 1.244,
        "ReadoutFidelity": 0.8893,
        "SingleGateFidelity": 0.9975,
        "FidelityMat": [
          [
            0.909,
            0.1304
          ],
          [
            0.091,
            0.8696
          ]
        ]
      },
      "57": {
        "Frequency": 4394,
        "T1": 9.33,
        "T2": 2.022,
        "ReadoutFidelity": 0.8774,
        "SingleGateFidelity": 0.9983,
        "FidelityMat": [
          [
            0.9284,
            0.1736
          ],
          [
            0.0716,
            0.8264
          ]
        ]
      },
      "60": {
        "Frequency": 4615,
        "T1": 6.702,
        "T2": 4.079,
        "ReadoutFidelity": 0.8578,
        "SingleGateFidelity": 0.9982,
        "FidelityMat": [
          [
            0.9484,
            0.2328
          ],
          [
            0.0516,
            0.7672
          ]
        ]
      },
      "61": {
        "Frequency": 3978.968,
        "T1": 16.445,
        "T2": 1.286,
        "ReadoutFidelity": 0.8219,
        "SingleGateFidelity": 0.9958,
        "FidelityMat": [
          [
            0.9112,
            0.2674
          ],
          [
            0.0888,
            0.7326
          ]
        ]
      },
      "62": {
        "Frequency": 4532,
        "T1": 9.74,
        "T2": 2.128,
        "ReadoutFidelity": 0.913,
        "SingleGateFidelity": 0.998,
        "FidelityMat": [
          [
            0.9464,
            0.1204
          ],
          [
            0.0536,
            0.8796
          ]
        ]
      },
      "65": {
        "Frequency": 4078,
        "T1": 10.14,
        "T2": 2.789,
        "ReadoutFidelity": 0.8949,
        "SingleGateFidelity": 0.9975,
        "FidelityMat": [
          [
            0.9336,
            0.1438
          ],
          [
            0.0664,
            0.8562
          ]
        ]
      },
      "66": {
        "Frequency": 4204,
        "T1": 12.559,
        "T2": 3.531,
        "ReadoutFidelity": 0.8756,
        "SingleGateFidelity": 0.9983,
        "FidelityMat": [
          [
            0.9078,
            0.1566
          ],
          [
            0.0922,
            0.8434
          ]
        ]
      },
      "67": {
        "Frequency": 4663,
        "T1": 12.332,
        "T2": 2.336,
        "ReadoutFidelity": 0.8673,
        "SingleGateFidelity": 0.9975,
        "FidelityMat": [
          [
            0.9698,
            0.2352
          ],
          [
            0.0302,
            0.7648
          ]
        ]
      },
      "68": {
        "Frequency": 4085,
        "T1": 33.042,
        "T2": 4.434,
        "ReadoutFidelity": 0.9001,
        "SingleGateFidelity": 0.998,
        "FidelityMat": [
          [
            0.927,
            0.1268
          ],
          [
            0.073,
            0.8732
          ]
        ]
      },
      "70": {
        "Frequency": 4227,
        "T1": 9.146,
        "T2": 1.744,
        "ReadoutFidelity": 0.8698,
        "SingleGateFidelity": 0.9968,
        "FidelityMat": [
          [
            0.927,
            0.1874
          ],
          [
            0.073,
            0.8126
          ]
        ]
      },
      "71": {
        "Frequency": 4642,
        "T1": 0.0,
        "T2": 0.0,
        "ReadoutFidelity": 0.8788,
        "SingleGateFidelity": 0.9983,
        "FidelityMat": [
          [
            0.943,
            0.1854
          ],
          [
            0.057,
            0.8146
          ]
        ]
      }
    },
    "AvailableQubits": [
      0,
      1,
      2,
      3,
      4,
      6,
      7,
      8,
      9,
      10,
      11,
      12,
      13,
      14,
      15,
      16,
      17,
      18,
      19,
      20,
      22,
      24,
      25,
      26,
      27,
      28,
      29,
      30,
      31,
      32,
      33,
      34,
      35,
      36,
      37,
      38,
      39,
      40,
      41,
      42,
      44,
      45,
      46,
      47,
      48,
      49,
      50,
      52,
      54,
      56,
      57,
      60,
      61,
      62,
      65,
      66,
      67,
      68,
      70,
      71
    ],
    "QGateClock": {
      "CZ": 40,
      "RPhi": 30,
      "ECHO": 0,
      "IDLE": 0,
      "BARRIER": 0
    },
    "BasicQGate": [
      "RPhi",
      "CZ"
    ],
    "LastUpdateTime": 1717395244425,
    "MaxClockCycle": 1000000,
    "MaxShots": 20000,
    "calc_method": 0
  },
  "noise_model_double": {
    "model": "DEPOLARIZING_KRAUS_OPERATOR",
    "gate": "CZ_GATE",
    "prob": [
      0.002,
      0.003
    ]
  },
  "noise_model_single": {
    "model": "DEPOLARIZING_KRAUS_OPERATOR",
    "gate": "RPHI_GATE",
    "prob": [
      0.01,
      0.002
    ]
  },
  "noise_learning_config": {
    "pattern": 0,
    "file": "common_generator.py",
    "samples": 40,
    "nl_shots": 256,
    "depths": [
      2,
      4,
      8,
      16,
      32
    ],
    "qem_base_method": 0
  },
  "em_compute_config": {
    "pattern": 0,
    "file": "common_generator.py",
    "samples": 10,
    "nl_shots": 256,
    "depths": [
      2,
      4,
      8,
      16,
      32
    ],
    "qem_base_method": 0,
    "qem_method": 0,
    "noise_model_file": "common_PER_experiment.pkl",
    "qem_samples": 300,
    "qem_shots": 256,
    "expectations": [],
    "noise_strength": [
      1.0,
      1.3,
      1.5,
      1.8
    ]
  }
}
